LICENSE.txt
MANIFEST.in
README.md
setup.cfg
setup.py
snipsneopixel/__init__.py
snipsneopixel/lights.py
snipsneopixel/snipsneopixel.py
snipsneopixel.egg-info/PKG-INFO
snipsneopixel.egg-info/SOURCES.txt
snipsneopixel.egg-info/dependency_links.txt
snipsneopixel.egg-info/requires.txt
snipsneopixel.egg-info/top_level.txt