Metadata-Version: 1.0
Name: snipsneopixel
Version: 0.1.0
Summary: NeoPixel skill for Snips
Home-page: https://github.com/snipsco/snips-skill-neopixel
Author: UNKNOWN
Author-email: UNKNOWN
License: MIT
Keywords: snips,neopixel
Platform: UNKNOWN
